robot_ai/__init__.py
robot_ai/index.py
robot_ai/mcp_index.py
robot_ai/sync_mcp_client.py
robot_ai-0.3.2.dist-info/METADATA
robot_ai-0.3.2.dist-info/WHEEL
robot_ai-0.3.2.dist-info/RECORD
